rasterprynt/__init__.py
rasterprynt/__main__.py
rasterprynt-1.0.5.dist-info/METADATA
rasterprynt-1.0.5.dist-info/RECORD
rasterprynt-1.0.5.dist-info/WHEEL
rasterprynt-1.0.5.dist-info/top_level.txt
