Metadata-Version: 2.1
Name: rasterprynt
Version: 1.0.5
Summary: Print raster graphics on Brother P950NW and 9800PCN
Home-page: https://github.com/boxine/rasterprynt/
Author: Philipp Hagemeister (Boxine GmbH)
Author-email: philipp.hagemeister@boxine.de
License: MIT
Platform: UNKNOWN
Requires-Dist: Pillow
